_boot.pyi
_boot_fat.pyi
_onewire.pyi
_rp2.pyi
_thread.pyi
_uasyncio.pyi
array.pyi
binascii.pyi
cmath.pyi
collections.pyi
cryptolib.pyi
dht.pyi
ds18x20.pyi
errno.pyi
framebuf.pyi
gc.pyi
hashlib.pyi
heapq.pyi
io.pyi
json.pyi
logging.pyi
machine.pyi
math.pyi
micropython.pyi
micropython_.pyi
neopixel.pyi
onewire.pyi
os.pyi
random.pyi
rp2.pyi
select.pyi
struct.pyi
sys.pyi
time.pyi
uarray.pyi
uasyncio/__init__.pyi
uasyncio/core.pyi
uasyncio/event.pyi
uasyncio/funcs.pyi
uasyncio/lock.pyi
uasyncio/stream.pyi
uasyncio/task.pyi
ubinascii.pyi
ucollections.pyi
ucryptolib.pyi
uctypes.pyi
uerrno.pyi
uhashlib.pyi
uheapq.pyi
uio.pyi
ujson.pyi
umachine.pyi
uos.pyi
urandom.pyi
ure.pyi
uselect.pyi
ustruct.pyi
usys.pyi
utime.pyi
uzlib.pyi
zlib.pyi
micropython_rp2_pimoroni_picolipo_16mb_stubs-1.20.0.post2.dist-info/LICENSE.md
micropython_rp2_pimoroni_picolipo_16mb_stubs-1.20.0.post2.dist-info/METADATA
micropython_rp2_pimoroni_picolipo_16mb_stubs-1.20.0.post2.dist-info/WHEEL
micropython_rp2_pimoroni_picolipo_16mb_stubs-1.20.0.post2.dist-info/RECORD
